CITATION.cff
LICENSE.txt
spice_melange/__init__.py
spice_melange-0.1.0.dist-info/WHEEL
spice_melange-0.1.0.dist-info/LICENSE.txt
spice_melange-0.1.0.dist-info/METADATA
spice_melange-0.1.0.dist-info/RECORD
